nester.py
nester_wrj/__init__.py
nester_wrj/nester_wrj.py
nester_wrj-0.0.7.dist-info/METADATA
nester_wrj-0.0.7.dist-info/WHEEL
nester_wrj-0.0.7.dist-info/top_level.txt
nester_wrj-0.0.7.dist-info/RECORD
