Metadata-Version: 2.1
Name: nester-wrj
Version: 0.0.7
Summary: lalal!
Home-page: https://github.com/JeckerWen
Author: WenRj
Author-email: jeckerWen@gmail.com
License: UNKNOWN
Platform: UNKNOWN
Classifier: Programming Language :: Python :: 3
Classifier: License :: OSI Approved :: MIT License
Classifier: Operating System :: OS Independent
